wang/__init__.py
wang/wang_message.py
wangwang-0.0.4.dist-info/METADATA
wangwang-0.0.4.dist-info/WHEEL
wangwang-0.0.4.dist-info/top_level.txt
wangwang-0.0.4.dist-info/RECORD
