Metadata-Version: 2.1
Name: wangwang
Version: 0.0.4
Summary: 钉钉群消息推送
Home-page: UNKNOWN
Author: ZERONE
Author-email: zerone40@163.com
License: UNKNOWN
Keywords: wangwang dingding
Platform: UNKNOWN
Classifier: Programming Language :: Python :: 3
Classifier: License :: OSI Approved :: MIT License
Classifier: Operating System :: OS Independent
